{"diagram": {"data": {"id": "diagram-0", "name": "DIPAM for Textual anlysis", "type": "diagram"}}, "edges": [{"data": {"id": "e-0003", "name": "e-0003", "source": "t-0001", "target": "t-0003", "type": "edge", "value": ""}}, {"data": {"id": "e-0004", "name": "e-0004", "source": "d-0001", "target": "t-0001", "type": "edge", "value": ""}}, {"data": {"id": "e-0001", "name": "e-0001", "source": "t-0001", "target": "t-0002", "type": "edge", "value": ""}}], "nodes": [{"data": {"graph": {"position": {"x": 616.5640900645074, "y": -131.46738034911016}}, "id": "d-0001", "name": "AH Documents", "param": {"p-file": {"0": {}, "1": {}, "2": {}, "3": {}, "4": {}, "5": {}, "6": {}, "7": {}, "8": {}, "9": {}}}, "type": "data", "value": "d-gen-text"}}, {"data": {"graph": {"position": {"x": 617.9609914840707, "y": 4.231578392168915}}, "id": "t-0001", "name": "LDA Topic Modelling", "param": {"p-defstopwords": "english", "p-numwords": "25", "p-topic": "10"}, "type": "tool", "value": "t-topic-lda"}}, {"data": {"graph": {"position": {"x": 511.9561735406341, "y": 103.31424689929598}}, "id": "t-0002", "name": "Save-LDA", "param": {}, "type": "tool", "value": "t-save-files"}}, {"data": {"graph": {"position": {"x": 818.5661981936487, "y": 6.4593613527630485}}, "id": "t-0003", "name": "Visualize Topics", "param": {}, "type": "tool", "value": "t-topics-view"}}]}